[
  {
    "date": "2026-03-28",
    "providers": {
      "skrill": {
        "rate": 24.894,
        "fee": 0,
        "markup": 2.75,
        "receiveAmount": 2489.4
      },
      "currencyfair": {
        "rate": 25.3312,
        "fee": 34.74,
        "markup": 1.04,
        "receiveAmount": 1653.11
      },
      "paysend": {
        "rate": 24.8276,
        "fee": 0,
        "markup": 3.01,
        "receiveAmount": 2482.76
      },
      "remitly": {
        "rate": 25.62,
        "fee": 5,
        "markup": null,
        "receiveAmount": 2562
      },
      "taptap-send": {
        "rate": 25.6,
        "fee": 0,
        "markup": null,
        "receiveAmount": 2560
      },
      "wise": {
        "rate": 25.7769,
        "fee": 0,
        "markup": null,
        "receiveAmount": 2577.69
      }
    }
  },
  {
    "date": "2026-03-29",
    "providers": {
      "skrill": {
        "rate": 24.894,
        "fee": 0,
        "markup": 2.75,
        "receiveAmount": 2489.4
      },
      "currencyfair": {
        "rate": 25.3312,
        "fee": 34.74,
        "markup": 1.04,
        "receiveAmount": 1653.11
      },
      "paysend": {
        "rate": 24.8276,
        "fee": 0,
        "markup": 3.01,
        "receiveAmount": 2482.76
      },
      "remitly": {
        "rate": 25.62,
        "fee": 5,
        "markup": null,
        "receiveAmount": 2562
      },
      "taptap-send": {
        "rate": 25.7,
        "fee": 0,
        "markup": null,
        "receiveAmount": 2570
      },
      "wise": {
        "rate": 25.7909,
        "fee": 0,
        "markup": null,
        "receiveAmount": 2579.09
      }
    }
  },
  {
    "date": "2026-03-30",
    "providers": {
      "skrill": {
        "rate": 24.894,
        "fee": 0,
        "markup": 2.75,
        "receiveAmount": 2489.4
      },
      "currencyfair": {
        "rate": 25.3312,
        "fee": 34.74,
        "markup": 1.04,
        "receiveAmount": 1653.11
      },
      "paysend": {
        "rate": 24.8276,
        "fee": 0,
        "markup": 3.01,
        "receiveAmount": 2482.76
      },
      "remitly": {
        "rate": 25.62,
        "fee": 5,
        "markup": null,
        "receiveAmount": 2562
      },
      "taptap-send": {
        "rate": 25.5,
        "fee": 0,
        "markup": null,
        "receiveAmount": 2550
      },
      "wise": {
        "rate": 25.7974,
        "fee": 0,
        "markup": null,
        "receiveAmount": 2579.74
      },
      "xoom": {
        "rate": 94.5609,
        "fee": 0,
        "markup": null,
        "receiveAmount": 9456
      }
    }
  }
]