[
  {
    "date": "2026-05-14",
    "providers": {
      "taptap-send": {
        "rate": 1353.37,
        "fee": 0,
        "markup": null,
        "receiveAmount": 135337
      }
    }
  },
  {
    "date": "2026-05-15",
    "providers": {
      "taptap-send": {
        "rate": 1348.16,
        "fee": 0,
        "markup": null,
        "receiveAmount": 134816
      }
    }
  },
  {
    "date": "2026-05-16",
    "providers": {
      "taptap-send": {
        "rate": 1344.96,
        "fee": 0,
        "markup": null,
        "receiveAmount": 134496
      }
    }
  },
  {
    "date": "2026-05-17",
    "providers": {
      "taptap-send": {
        "rate": 1346.27,
        "fee": 0,
        "markup": null,
        "receiveAmount": 134627
      }
    }
  },
  {
    "date": "2026-05-18",
    "providers": {
      "taptap-send": {
        "rate": 1344.03,
        "fee": 0,
        "markup": null,
        "receiveAmount": 134403
      }
    }
  }
]