[
  {
    "provider": "OFX",
    "providerSlug": "ofx",
    "providerType": "moneyTransferProvider",
    "sendCurrency": "USD",
    "receiveCurrency": "INR",
    "sendAmount": 500,
    "fee": 5,
    "exchangeRate": 88.8768,
    "interbankRate": 92.578,
    "markup": 4,
    "receiveAmount": 44438.4,
    "paymentMethod": null,
    "deliveryEstimate": "2 days",
    "deliveryMethod": null,
    "dateCollected": "2026-04-17T01:44:45.562Z",
    "source": "ofx-api"
  },
  {
    "provider": "OFX",
    "providerSlug": "ofx",
    "providerType": "moneyTransferProvider",
    "sendCurrency": "USD",
    "receiveCurrency": "INR",
    "sendAmount": 1000,
    "fee": 5,
    "exchangeRate": 89.317,
    "interbankRate": 92.577,
    "markup": 3.52,
    "receiveAmount": 89317,
    "paymentMethod": null,
    "deliveryEstimate": "2 days",
    "deliveryMethod": null,
    "dateCollected": "2026-04-17T01:44:47.364Z",
    "source": "ofx-api"
  },
  {
    "provider": "OFX",
    "providerSlug": "ofx",
    "providerType": "moneyTransferProvider",
    "sendCurrency": "USD",
    "receiveCurrency": "PHP",
    "sendAmount": 500,
    "fee": 5,
    "exchangeRate": 56.2274,
    "interbankRate": 59.9,
    "markup": 6.13,
    "receiveAmount": 28113.7,
    "paymentMethod": null,
    "deliveryEstimate": "2 days",
    "deliveryMethod": null,
    "dateCollected": "2026-04-17T01:44:49.148Z",
    "source": "ofx-api"
  },
  {
    "provider": "OFX",
    "providerSlug": "ofx",
    "providerType": "moneyTransferProvider",
    "sendCurrency": "USD",
    "receiveCurrency": "PHP",
    "sendAmount": 1000,
    "fee": 5,
    "exchangeRate": 57.5048,
    "interbankRate": 59.9,
    "markup": 4,
    "receiveAmount": 57504.8,
    "paymentMethod": null,
    "deliveryEstimate": "2 days",
    "deliveryMethod": null,
    "dateCollected": "2026-04-17T01:44:51.061Z",
    "source": "ofx-api"
  },
  {
    "provider": "OFX",
    "providerSlug": "ofx",
    "providerType": "moneyTransferProvider",
    "sendCurrency": "USD",
    "receiveCurrency": "IDR",
    "sendAmount": 500,
    "fee": 5,
    "exchangeRate": 15960.9243,
    "interbankRate": 17003,
    "markup": 6.13,
    "receiveAmount": 7980462.15,
    "paymentMethod": null,
    "deliveryEstimate": "2 days",
    "deliveryMethod": null,
    "dateCollected": "2026-04-17T01:44:52.830Z",
    "source": "ofx-api"
  },
  {
    "provider": "OFX",
    "providerSlug": "ofx",
    "providerType": "moneyTransferProvider",
    "sendCurrency": "USD",
    "receiveCurrency": "IDR",
    "sendAmount": 1000,
    "fee": 5,
    "exchangeRate": 16323.5191,
    "interbankRate": 17006,
    "markup": 4.01,
    "receiveAmount": 16323519.1,
    "paymentMethod": null,
    "deliveryEstimate": "2 days",
    "deliveryMethod": null,
    "dateCollected": "2026-04-17T01:44:54.665Z",
    "source": "ofx-api"
  },
  {
    "provider": "OFX",
    "providerSlug": "ofx",
    "providerType": "moneyTransferProvider",
    "sendCurrency": "USD",
    "receiveCurrency": "THB",
    "sendAmount": 500,
    "fee": 5,
    "exchangeRate": 30.743,
    "interbankRate": 32.023,
    "markup": 4,
    "receiveAmount": 15371.5,
    "paymentMethod": null,
    "deliveryEstimate": null,
    "deliveryMethod": null,
    "dateCollected": "2026-04-17T01:44:56.518Z",
    "source": "ofx-api"
  },
  {
    "provider": "OFX",
    "providerSlug": "ofx",
    "providerType": "moneyTransferProvider",
    "sendCurrency": "USD",
    "receiveCurrency": "THB",
    "sendAmount": 1000,
    "fee": 5,
    "exchangeRate": 31.1616,
    "interbankRate": 32.025,
    "markup": 2.7,
    "receiveAmount": 31161.6,
    "paymentMethod": null,
    "deliveryEstimate": null,
    "deliveryMethod": null,
    "dateCollected": "2026-04-17T01:44:58.293Z",
    "source": "ofx-api"
  },
  {
    "provider": "OFX",
    "providerSlug": "ofx",
    "providerType": "moneyTransferProvider",
    "sendCurrency": "USD",
    "receiveCurrency": "MYR",
    "sendAmount": 500,
    "fee": 5,
    "exchangeRate": 3.7234,
    "interbankRate": 3.9424,
    "markup": 5.55,
    "receiveAmount": 1861.7,
    "paymentMethod": null,
    "deliveryEstimate": "2 days",
    "deliveryMethod": null,
    "dateCollected": "2026-04-17T01:45:00.060Z",
    "source": "ofx-api"
  },
  {
    "provider": "OFX",
    "providerSlug": "ofx",
    "providerType": "moneyTransferProvider",
    "sendCurrency": "USD",
    "receiveCurrency": "MYR",
    "sendAmount": 1000,
    "fee": 5,
    "exchangeRate": 3.7999,
    "interbankRate": 3.9426,
    "markup": 3.62,
    "receiveAmount": 3799.9,
    "paymentMethod": null,
    "deliveryEstimate": "2 days",
    "deliveryMethod": null,
    "dateCollected": "2026-04-17T01:45:01.920Z",
    "source": "ofx-api"
  },
  {
    "provider": "OFX",
    "providerSlug": "ofx",
    "providerType": "moneyTransferProvider",
    "sendCurrency": "USD",
    "receiveCurrency": "TRY",
    "sendAmount": 500,
    "fee": 5,
    "exchangeRate": 43.0478,
    "interbankRate": 44.8435,
    "markup": 4,
    "receiveAmount": 21523.9,
    "paymentMethod": null,
    "deliveryEstimate": "2 days",
    "deliveryMethod": null,
    "dateCollected": "2026-04-17T01:45:03.697Z",
    "source": "ofx-api"
  },
  {
    "provider": "OFX",
    "providerSlug": "ofx",
    "providerType": "moneyTransferProvider",
    "sendCurrency": "USD",
    "receiveCurrency": "TRY",
    "sendAmount": 1000,
    "fee": 5,
    "exchangeRate": 43.6685,
    "interbankRate": 44.8405,
    "markup": 2.61,
    "receiveAmount": 43668.5,
    "paymentMethod": null,
    "deliveryEstimate": "2 days",
    "deliveryMethod": null,
    "dateCollected": "2026-04-17T01:45:05.652Z",
    "source": "ofx-api"
  },
  {
    "provider": "OFX",
    "providerSlug": "ofx",
    "providerType": "moneyTransferProvider",
    "sendCurrency": "USD",
    "receiveCurrency": "MXN",
    "sendAmount": 500,
    "fee": 5,
    "exchangeRate": 16.5534,
    "interbankRate": 17.2441,
    "markup": 4.01,
    "receiveAmount": 8276.7,
    "paymentMethod": null,
    "deliveryEstimate": null,
    "deliveryMethod": null,
    "dateCollected": "2026-04-17T01:45:07.399Z",
    "source": "ofx-api"
  },
  {
    "provider": "OFX",
    "providerSlug": "ofx",
    "providerType": "moneyTransferProvider",
    "sendCurrency": "USD",
    "receiveCurrency": "MXN",
    "sendAmount": 1000,
    "fee": 5,
    "exchangeRate": 16.7788,
    "interbankRate": 17.2411,
    "markup": 2.68,
    "receiveAmount": 16778.8,
    "paymentMethod": null,
    "deliveryEstimate": null,
    "deliveryMethod": null,
    "dateCollected": "2026-04-17T01:45:09.172Z",
    "source": "ofx-api"
  },
  {
    "provider": "OFX",
    "providerSlug": "ofx",
    "providerType": "moneyTransferProvider",
    "sendCurrency": "USD",
    "receiveCurrency": "EUR",
    "sendAmount": 500,
    "fee": 5,
    "exchangeRate": 0.8166,
    "interbankRate": 0.8487694199,
    "markup": 3.79,
    "receiveAmount": 408.3,
    "paymentMethod": null,
    "deliveryEstimate": "1 day",
    "deliveryMethod": null,
    "dateCollected": "2026-04-17T01:45:11.099Z",
    "source": "ofx-api"
  },
  {
    "provider": "OFX",
    "providerSlug": "ofx",
    "providerType": "moneyTransferProvider",
    "sendCurrency": "USD",
    "receiveCurrency": "EUR",
    "sendAmount": 1000,
    "fee": 5,
    "exchangeRate": 0.8282,
    "interbankRate": 0.8492694199,
    "markup": 2.48,
    "receiveAmount": 828.2,
    "paymentMethod": null,
    "deliveryEstimate": "1 day",
    "deliveryMethod": null,
    "dateCollected": "2026-04-17T01:45:12.911Z",
    "source": "ofx-api"
  },
  {
    "provider": "OFX",
    "providerSlug": "ofx",
    "providerType": "moneyTransferProvider",
    "sendCurrency": "USD",
    "receiveCurrency": "GBP",
    "sendAmount": 500,
    "fee": 5,
    "exchangeRate": 0.713,
    "interbankRate": 0.739866854,
    "markup": 3.63,
    "receiveAmount": 356.5,
    "paymentMethod": null,
    "deliveryEstimate": null,
    "deliveryMethod": null,
    "dateCollected": "2026-04-17T01:45:14.703Z",
    "source": "ofx-api"
  },
  {
    "provider": "OFX",
    "providerSlug": "ofx",
    "providerType": "moneyTransferProvider",
    "sendCurrency": "USD",
    "receiveCurrency": "GBP",
    "sendAmount": 1000,
    "fee": 5,
    "exchangeRate": 0.7225,
    "interbankRate": 0.739366854,
    "markup": 2.28,
    "receiveAmount": 722.5,
    "paymentMethod": null,
    "deliveryEstimate": null,
    "deliveryMethod": null,
    "dateCollected": "2026-04-17T01:45:16.549Z",
    "source": "ofx-api"
  },
  {
    "provider": "OFX",
    "providerSlug": "ofx",
    "providerType": "moneyTransferProvider",
    "sendCurrency": "USD",
    "receiveCurrency": "PKR",
    "sendAmount": 500,
    "fee": 5,
    "exchangeRate": 267.5792,
    "interbankRate": 278.899,
    "markup": 4.06,
    "receiveAmount": 133789.6,
    "paymentMethod": null,
    "deliveryEstimate": "2 days",
    "deliveryMethod": null,
    "dateCollected": "2026-04-17T01:45:21.672Z",
    "source": "ofx-api"
  },
  {
    "provider": "OFX",
    "providerSlug": "ofx",
    "providerType": "moneyTransferProvider",
    "sendCurrency": "USD",
    "receiveCurrency": "PKR",
    "sendAmount": 1000,
    "fee": 5,
    "exchangeRate": 271.5936,
    "interbankRate": 278.919,
    "markup": 2.63,
    "receiveAmount": 271593.6,
    "paymentMethod": null,
    "deliveryEstimate": "2 days",
    "deliveryMethod": null,
    "dateCollected": "2026-04-17T01:45:23.457Z",
    "source": "ofx-api"
  },
  {
    "provider": "OFX",
    "providerSlug": "ofx",
    "providerType": "moneyTransferProvider",
    "sendCurrency": "USD",
    "receiveCurrency": "BRL",
    "sendAmount": 500,
    "fee": 5,
    "exchangeRate": 4.6148,
    "interbankRate": 4.8925,
    "markup": 5.68,
    "receiveAmount": 2307.4,
    "paymentMethod": null,
    "deliveryEstimate": "2 days",
    "deliveryMethod": null,
    "dateCollected": "2026-04-17T01:45:25.422Z",
    "source": "ofx-api"
  },
  {
    "provider": "OFX",
    "providerSlug": "ofx",
    "providerType": "moneyTransferProvider",
    "sendCurrency": "USD",
    "receiveCurrency": "BRL",
    "sendAmount": 1000,
    "fee": 5,
    "exchangeRate": 4.7116,
    "interbankRate": 4.8926,
    "markup": 3.7,
    "receiveAmount": 4711.6,
    "paymentMethod": null,
    "deliveryEstimate": "2 days",
    "deliveryMethod": null,
    "dateCollected": "2026-04-17T01:45:27.233Z",
    "source": "ofx-api"
  },
  {
    "provider": "OFX",
    "providerSlug": "ofx",
    "providerType": "moneyTransferProvider",
    "sendCurrency": "GBP",
    "receiveCurrency": "INR",
    "sendAmount": 500,
    "fee": 7,
    "exchangeRate": 120.878,
    "interbankRate": 125.10760860600698,
    "markup": 3.38,
    "receiveAmount": 60439,
    "paymentMethod": null,
    "deliveryEstimate": "2 days",
    "deliveryMethod": null,
    "dateCollected": "2026-04-17T01:45:35.708Z",
    "source": "ofx-api"
  },
  {
    "provider": "OFX",
    "providerSlug": "ofx",
    "providerType": "moneyTransferProvider",
    "sendCurrency": "GBP",
    "receiveCurrency": "INR",
    "sendAmount": 1000,
    "fee": 7,
    "exchangeRate": 121.1417,
    "interbankRate": 125.16760860600698,
    "markup": 3.22,
    "receiveAmount": 121141.7,
    "paymentMethod": null,
    "deliveryEstimate": "2 days",
    "deliveryMethod": null,
    "dateCollected": "2026-04-17T01:45:37.614Z",
    "source": "ofx-api"
  },
  {
    "provider": "OFX",
    "providerSlug": "ofx",
    "providerType": "moneyTransferProvider",
    "sendCurrency": "GBP",
    "receiveCurrency": "EUR",
    "sendAmount": 500,
    "fee": 7,
    "exchangeRate": 1.1207,
    "interbankRate": 1.1474129427171738,
    "markup": 2.33,
    "receiveAmount": 560.35,
    "paymentMethod": null,
    "deliveryEstimate": "1 day",
    "deliveryMethod": null,
    "dateCollected": "2026-04-17T01:45:39.363Z",
    "source": "ofx-api"
  },
  {
    "provider": "OFX",
    "providerSlug": "ofx",
    "providerType": "moneyTransferProvider",
    "sendCurrency": "GBP",
    "receiveCurrency": "EUR",
    "sendAmount": 1000,
    "fee": 7,
    "exchangeRate": 1.1232,
    "interbankRate": 1.147512942717174,
    "markup": 2.12,
    "receiveAmount": 1123.2,
    "paymentMethod": null,
    "deliveryEstimate": "1 day",
    "deliveryMethod": null,
    "dateCollected": "2026-04-17T01:45:41.189Z",
    "source": "ofx-api"
  },
  {
    "provider": "OFX",
    "providerSlug": "ofx",
    "providerType": "moneyTransferProvider",
    "sendCurrency": "GBP",
    "receiveCurrency": "USD",
    "sendAmount": 500,
    "fee": 7,
    "exchangeRate": 1.3221,
    "interbankRate": 1.3514700000648843,
    "markup": 2.17,
    "receiveAmount": 661.05,
    "paymentMethod": null,
    "deliveryEstimate": null,
    "deliveryMethod": null,
    "dateCollected": "2026-04-17T01:45:43.002Z",
    "source": "ofx-api"
  },
  {
    "provider": "OFX",
    "providerSlug": "ofx",
    "providerType": "moneyTransferProvider",
    "sendCurrency": "GBP",
    "receiveCurrency": "USD",
    "sendAmount": 1000,
    "fee": 7,
    "exchangeRate": 1.325,
    "interbankRate": 1.3514700000648843,
    "markup": 1.96,
    "receiveAmount": 1325,
    "paymentMethod": null,
    "deliveryEstimate": null,
    "deliveryMethod": null,
    "dateCollected": "2026-04-17T01:45:44.771Z",
    "source": "ofx-api"
  },
  {
    "provider": "OFX",
    "providerSlug": "ofx",
    "providerType": "moneyTransferProvider",
    "sendCurrency": "EUR",
    "receiveCurrency": "INR",
    "sendAmount": 500,
    "fee": 10,
    "exchangeRate": 104.6622,
    "interbankRate": 109.01313380282207,
    "markup": 3.99,
    "receiveAmount": 52331.1,
    "paymentMethod": null,
    "deliveryEstimate": "2 days",
    "deliveryMethod": null,
    "dateCollected": "2026-04-17T01:45:49.870Z",
    "source": "ofx-api"
  },
  {
    "provider": "OFX",
    "providerSlug": "ofx",
    "providerType": "moneyTransferProvider",
    "sendCurrency": "EUR",
    "receiveCurrency": "INR",
    "sendAmount": 1000,
    "fee": 10,
    "exchangeRate": 105.3234,
    "interbankRate": 109.04313380282207,
    "markup": 3.41,
    "receiveAmount": 105323.4,
    "paymentMethod": null,
    "deliveryEstimate": "2 days",
    "deliveryMethod": null,
    "dateCollected": "2026-04-17T01:45:51.744Z",
    "source": "ofx-api"
  },
  {
    "provider": "OFX",
    "providerSlug": "ofx",
    "providerType": "moneyTransferProvider",
    "sendCurrency": "EUR",
    "receiveCurrency": "GBP",
    "sendAmount": 500,
    "fee": 10,
    "exchangeRate": 0.8465,
    "interbankRate": 0.8710939867977306,
    "markup": 2.82,
    "receiveAmount": 423.25,
    "paymentMethod": null,
    "deliveryEstimate": null,
    "deliveryMethod": null,
    "dateCollected": "2026-04-17T01:45:53.499Z",
    "source": "ofx-api"
  },
  {
    "provider": "OFX",
    "providerSlug": "ofx",
    "providerType": "moneyTransferProvider",
    "sendCurrency": "EUR",
    "receiveCurrency": "GBP",
    "sendAmount": 1000,
    "fee": 10,
    "exchangeRate": 0.8519,
    "interbankRate": 0.8711939867977306,
    "markup": 2.21,
    "receiveAmount": 851.9,
    "paymentMethod": null,
    "deliveryEstimate": null,
    "deliveryMethod": null,
    "dateCollected": "2026-04-17T01:45:55.415Z",
    "source": "ofx-api"
  },
  {
    "provider": "OFX",
    "providerSlug": "ofx",
    "providerType": "moneyTransferProvider",
    "sendCurrency": "EUR",
    "receiveCurrency": "USD",
    "sendAmount": 500,
    "fee": 10,
    "exchangeRate": 1.1447,
    "interbankRate": 1.1778200000800665,
    "markup": 2.81,
    "receiveAmount": 572.35,
    "paymentMethod": null,
    "deliveryEstimate": null,
    "deliveryMethod": null,
    "dateCollected": "2026-04-17T01:45:57.261Z",
    "source": "ofx-api"
  },
  {
    "provider": "OFX",
    "providerSlug": "ofx",
    "providerType": "moneyTransferProvider",
    "sendCurrency": "EUR",
    "receiveCurrency": "USD",
    "sendAmount": 1000,
    "fee": 10,
    "exchangeRate": 1.152,
    "interbankRate": 1.1774200000800663,
    "markup": 2.16,
    "receiveAmount": 1152,
    "paymentMethod": null,
    "deliveryEstimate": null,
    "deliveryMethod": null,
    "dateCollected": "2026-04-17T01:45:59.209Z",
    "source": "ofx-api"
  },
  {
    "provider": "OFX",
    "providerSlug": "ofx",
    "providerType": "moneyTransferProvider",
    "sendCurrency": "CAD",
    "receiveCurrency": "INR",
    "sendAmount": 500,
    "fee": 15,
    "exchangeRate": 64.8565,
    "interbankRate": 67.55988963484047,
    "markup": 4,
    "receiveAmount": 32428.25,
    "paymentMethod": null,
    "deliveryEstimate": "2 days",
    "deliveryMethod": null,
    "dateCollected": "2026-04-17T01:46:04.303Z",
    "source": "ofx-api"
  },
  {
    "provider": "OFX",
    "providerSlug": "ofx",
    "providerType": "moneyTransferProvider",
    "sendCurrency": "CAD",
    "receiveCurrency": "INR",
    "sendAmount": 1000,
    "fee": 15,
    "exchangeRate": 65.1734,
    "interbankRate": 67.55788963484048,
    "markup": 3.53,
    "receiveAmount": 65173.4,
    "paymentMethod": null,
    "deliveryEstimate": "2 days",
    "deliveryMethod": null,
    "dateCollected": "2026-04-17T01:46:06.119Z",
    "source": "ofx-api"
  },
  {
    "provider": "OFX",
    "providerSlug": "ofx",
    "providerType": "moneyTransferProvider",
    "sendCurrency": "CAD",
    "receiveCurrency": "USD",
    "sendAmount": 500,
    "fee": 15,
    "exchangeRate": 0.7005,
    "interbankRate": 0.729435252050556,
    "markup": 3.97,
    "receiveAmount": 350.25,
    "paymentMethod": null,
    "deliveryEstimate": null,
    "deliveryMethod": null,
    "dateCollected": "2026-04-17T01:46:07.900Z",
    "source": "ofx-api"
  },
  {
    "provider": "OFX",
    "providerSlug": "ofx",
    "providerType": "moneyTransferProvider",
    "sendCurrency": "CAD",
    "receiveCurrency": "USD",
    "sendAmount": 1000,
    "fee": 15,
    "exchangeRate": 0.7128,
    "interbankRate": 0.729435252050556,
    "markup": 2.28,
    "receiveAmount": 712.8,
    "paymentMethod": null,
    "deliveryEstimate": null,
    "deliveryMethod": null,
    "dateCollected": "2026-04-17T01:46:09.789Z",
    "source": "ofx-api"
  },
  {
    "provider": "OFX",
    "providerSlug": "ofx",
    "providerType": "moneyTransferProvider",
    "sendCurrency": "AUD",
    "receiveCurrency": "INR",
    "sendAmount": 500,
    "fee": 15,
    "exchangeRate": 63.6678,
    "interbankRate": 66.31760880074093,
    "markup": 4,
    "receiveAmount": 31833.9,
    "paymentMethod": null,
    "deliveryEstimate": "2 days",
    "deliveryMethod": null,
    "dateCollected": "2026-04-17T01:46:11.589Z",
    "source": "ofx-api"
  },
  {
    "provider": "OFX",
    "providerSlug": "ofx",
    "providerType": "moneyTransferProvider",
    "sendCurrency": "AUD",
    "receiveCurrency": "INR",
    "sendAmount": 1000,
    "fee": 15,
    "exchangeRate": 64.0674,
    "interbankRate": 66.32260880074094,
    "markup": 3.4,
    "receiveAmount": 64067.4,
    "paymentMethod": null,
    "deliveryEstimate": "2 days",
    "deliveryMethod": null,
    "dateCollected": "2026-04-17T01:46:13.371Z",
    "source": "ofx-api"
  },
  {
    "provider": "OFX",
    "providerSlug": "ofx",
    "providerType": "moneyTransferProvider",
    "sendCurrency": "AUD",
    "receiveCurrency": "USD",
    "sendAmount": 500,
    "fee": 15,
    "exchangeRate": 0.6877,
    "interbankRate": 0.7165600000080031,
    "markup": 4.03,
    "receiveAmount": 343.85,
    "paymentMethod": null,
    "deliveryEstimate": null,
    "deliveryMethod": null,
    "dateCollected": "2026-04-17T01:46:15.279Z",
    "source": "ofx-api"
  },
  {
    "provider": "OFX",
    "providerSlug": "ofx",
    "providerType": "moneyTransferProvider",
    "sendCurrency": "AUD",
    "receiveCurrency": "USD",
    "sendAmount": 1000,
    "fee": 15,
    "exchangeRate": 0.7007,
    "interbankRate": 0.7160600000080032,
    "markup": 2.15,
    "receiveAmount": 700.7,
    "paymentMethod": null,
    "deliveryEstimate": null,
    "deliveryMethod": null,
    "dateCollected": "2026-04-17T01:46:17.272Z",
    "source": "ofx-api"
  },
  {
    "provider": "OFX",
    "providerSlug": "ofx",
    "providerType": "moneyTransferProvider",
    "sendCurrency": "AED",
    "receiveCurrency": "INR",
    "sendAmount": 500,
    "fee": 50,
    "exchangeRate": 24.1842,
    "interbankRate": 25.18883673469388,
    "markup": 3.99,
    "receiveAmount": 12092.1,
    "paymentMethod": null,
    "deliveryEstimate": "2 days",
    "deliveryMethod": null,
    "dateCollected": "2026-04-17T01:46:19.133Z",
    "source": "ofx-api"
  },
  {
    "provider": "OFX",
    "providerSlug": "ofx",
    "providerType": "moneyTransferProvider",
    "sendCurrency": "AED",
    "receiveCurrency": "INR",
    "sendAmount": 1000,
    "fee": 50,
    "exchangeRate": 24.1842,
    "interbankRate": 25.189836734693877,
    "markup": 3.99,
    "receiveAmount": 24184.2,
    "paymentMethod": null,
    "deliveryEstimate": "2 days",
    "deliveryMethod": null,
    "dateCollected": "2026-04-17T01:46:20.891Z",
    "source": "ofx-api"
  },
  {
    "provider": "OFX",
    "providerSlug": "ofx",
    "providerType": "moneyTransferProvider",
    "sendCurrency": "SGD",
    "receiveCurrency": "INR",
    "sendAmount": 500,
    "fee": 15,
    "exchangeRate": 69.808,
    "interbankRate": 72.71970489176537,
    "markup": 4,
    "receiveAmount": 34904,
    "paymentMethod": null,
    "deliveryEstimate": "2 days",
    "deliveryMethod": null,
    "dateCollected": "2026-04-17T01:46:22.660Z",
    "source": "ofx-api"
  },
  {
    "provider": "OFX",
    "providerSlug": "ofx",
    "providerType": "moneyTransferProvider",
    "sendCurrency": "SGD",
    "receiveCurrency": "INR",
    "sendAmount": 1000,
    "fee": 15,
    "exchangeRate": 70.1647,
    "interbankRate": 72.71870489176537,
    "markup": 3.51,
    "receiveAmount": 70164.7,
    "paymentMethod": null,
    "deliveryEstimate": "2 days",
    "deliveryMethod": null,
    "dateCollected": "2026-04-17T01:46:24.435Z",
    "source": "ofx-api"
  },
  {
    "provider": "OFX",
    "providerSlug": "ofx",
    "providerType": "moneyTransferProvider",
    "sendCurrency": "SGD",
    "receiveCurrency": "PHP",
    "sendAmount": 500,
    "fee": 15,
    "exchangeRate": 43.9916,
    "interbankRate": 47.04886019039241,
    "markup": 6.5,
    "receiveAmount": 21995.8,
    "paymentMethod": null,
    "deliveryEstimate": "2 days",
    "deliveryMethod": null,
    "dateCollected": "2026-04-17T01:46:26.398Z",
    "source": "ofx-api"
  },
  {
    "provider": "OFX",
    "providerSlug": "ofx",
    "providerType": "moneyTransferProvider",
    "sendCurrency": "SGD",
    "receiveCurrency": "PHP",
    "sendAmount": 1000,
    "fee": 15,
    "exchangeRate": 45.1743,
    "interbankRate": 47.051229745120374,
    "markup": 3.99,
    "receiveAmount": 45174.3,
    "paymentMethod": null,
    "deliveryEstimate": "2 days",
    "deliveryMethod": null,
    "dateCollected": "2026-04-17T01:46:28.188Z",
    "source": "ofx-api"
  },
  {
    "provider": "OFX",
    "providerSlug": "ofx",
    "providerType": "moneyTransferProvider",
    "sendCurrency": "NZD",
    "receiveCurrency": "INR",
    "sendAmount": 500,
    "fee": 12,
    "exchangeRate": 52.2809,
    "interbankRate": 54.45825920028188,
    "markup": 4,
    "receiveAmount": 26140.45,
    "paymentMethod": null,
    "deliveryEstimate": "2 days",
    "deliveryMethod": null,
    "dateCollected": "2026-04-17T01:46:29.948Z",
    "source": "ofx-api"
  },
  {
    "provider": "OFX",
    "providerSlug": "ofx",
    "providerType": "moneyTransferProvider",
    "sendCurrency": "NZD",
    "receiveCurrency": "INR",
    "sendAmount": 1000,
    "fee": 12,
    "exchangeRate": 52.5664,
    "interbankRate": 54.46125920028188,
    "markup": 3.48,
    "receiveAmount": 52566.4,
    "paymentMethod": null,
    "deliveryEstimate": "2 days",
    "deliveryMethod": null,
    "dateCollected": "2026-04-17T01:46:31.799Z",
    "source": "ofx-api"
  },
  {
    "provider": "OFX",
    "providerSlug": "ofx",
    "providerType": "moneyTransferProvider",
    "sendCurrency": "NZD",
    "receiveCurrency": "AUD",
    "sendAmount": 500,
    "fee": 12,
    "exchangeRate": 0.7881,
    "interbankRate": 0.8208450972771932,
    "markup": 3.99,
    "receiveAmount": 394.05,
    "paymentMethod": null,
    "deliveryEstimate": "1 day",
    "deliveryMethod": null,
    "dateCollected": "2026-04-17T01:46:33.558Z",
    "source": "ofx-api"
  },
  {
    "provider": "OFX",
    "providerSlug": "ofx",
    "providerType": "moneyTransferProvider",
    "sendCurrency": "NZD",
    "receiveCurrency": "AUD",
    "sendAmount": 1000,
    "fee": 12,
    "exchangeRate": 0.8024,
    "interbankRate": 0.8210450972771932,
    "markup": 2.27,
    "receiveAmount": 802.4,
    "paymentMethod": null,
    "deliveryEstimate": "1 day",
    "deliveryMethod": null,
    "dateCollected": "2026-04-17T01:46:35.397Z",
    "source": "ofx-api"
  },
  {
    "provider": "OFX",
    "providerSlug": "ofx",
    "providerType": "moneyTransferProvider",
    "sendCurrency": "CHF",
    "receiveCurrency": "INR",
    "sendAmount": 500,
    "fee": 15,
    "exchangeRate": 113.4182,
    "interbankRate": 118.15399836655521,
    "markup": 4.01,
    "receiveAmount": 56709.1,
    "paymentMethod": null,
    "deliveryEstimate": "2 days",
    "deliveryMethod": null,
    "dateCollected": "2026-04-17T01:46:37.175Z",
    "source": "ofx-api"
  },
  {
    "provider": "OFX",
    "providerSlug": "ofx",
    "providerType": "moneyTransferProvider",
    "sendCurrency": "CHF",
    "receiveCurrency": "INR",
    "sendAmount": 1000,
    "fee": 15,
    "exchangeRate": 113.4182,
    "interbankRate": 118.13399836655522,
    "markup": 3.99,
    "receiveAmount": 113418.2,
    "paymentMethod": null,
    "deliveryEstimate": "2 days",
    "deliveryMethod": null,
    "dateCollected": "2026-04-17T01:46:38.956Z",
    "source": "ofx-api"
  },
  {
    "provider": "OFX",
    "providerSlug": "ofx",
    "providerType": "moneyTransferProvider",
    "sendCurrency": "CHF",
    "receiveCurrency": "EUR",
    "sendAmount": 500,
    "fee": 15,
    "exchangeRate": 1.0401,
    "interbankRate": 1.0832298947193792,
    "markup": 3.98,
    "receiveAmount": 520.05,
    "paymentMethod": null,
    "deliveryEstimate": "1 day",
    "deliveryMethod": null,
    "dateCollected": "2026-04-17T01:46:40.774Z",
    "source": "ofx-api"
  },
  {
    "provider": "OFX",
    "providerSlug": "ofx",
    "providerType": "moneyTransferProvider",
    "sendCurrency": "CHF",
    "receiveCurrency": "EUR",
    "sendAmount": 1000,
    "fee": 15,
    "exchangeRate": 1.0459,
    "interbankRate": 1.0833298947193792,
    "markup": 3.46,
    "receiveAmount": 1045.9,
    "paymentMethod": null,
    "deliveryEstimate": "1 day",
    "deliveryMethod": null,
    "dateCollected": "2026-04-17T01:46:42.540Z",
    "source": "ofx-api"
  },
  {
    "provider": "OFX",
    "providerSlug": "ofx",
    "providerType": "moneyTransferProvider",
    "sendCurrency": "SAR",
    "receiveCurrency": "INR",
    "sendAmount": 500,
    "fee": 0,
    "exchangeRate": 22.8427,
    "interbankRate": 24.431663675946695,
    "markup": 6.5,
    "receiveAmount": 11421.35,
    "paymentMethod": null,
    "deliveryEstimate": "2 days",
    "deliveryMethod": null,
    "dateCollected": "2026-04-17T01:46:44.335Z",
    "source": "ofx-api"
  },
  {
    "provider": "OFX",
    "providerSlug": "ofx",
    "providerType": "moneyTransferProvider",
    "sendCurrency": "SAR",
    "receiveCurrency": "INR",
    "sendAmount": 1000,
    "fee": 0,
    "exchangeRate": 22.8427,
    "interbankRate": 24.432663675946696,
    "markup": 6.51,
    "receiveAmount": 22842.7,
    "paymentMethod": null,
    "deliveryEstimate": "2 days",
    "deliveryMethod": null,
    "dateCollected": "2026-04-17T01:46:46.133Z",
    "source": "ofx-api"
  },
  {
    "provider": "OFX",
    "providerSlug": "ofx",
    "providerType": "moneyTransferProvider",
    "sendCurrency": "SAR",
    "receiveCurrency": "PKR",
    "sendAmount": 500,
    "fee": 0,
    "exchangeRate": 68.8115,
    "interbankRate": 73.59619725557461,
    "markup": 6.5,
    "receiveAmount": 34405.75,
    "paymentMethod": null,
    "deliveryEstimate": "2 days",
    "deliveryMethod": null,
    "dateCollected": "2026-04-17T01:46:48.005Z",
    "source": "ofx-api"
  },
  {
    "provider": "OFX",
    "providerSlug": "ofx",
    "providerType": "moneyTransferProvider",
    "sendCurrency": "SAR",
    "receiveCurrency": "PKR",
    "sendAmount": 1000,
    "fee": 0,
    "exchangeRate": 68.8115,
    "interbankRate": 73.59719725557461,
    "markup": 6.5,
    "receiveAmount": 68811.5,
    "paymentMethod": null,
    "deliveryEstimate": "2 days",
    "deliveryMethod": null,
    "dateCollected": "2026-04-17T01:46:49.761Z",
    "source": "ofx-api"
  }
]